ncs_uml/__init__.py
ncs_uml/main.py
ncs_uml/utils.py
ncs_uml/plugins/__init__.py
ncs_uml/plugins/uml_patch.py
ncs_uml/scripts/__init__.py
ncs_uml/scripts/run.py
ncs_uml-1.2.2.dist-info/LICENSE
ncs_uml-1.2.2.dist-info/METADATA
ncs_uml-1.2.2.dist-info/WHEEL
ncs_uml-1.2.2.dist-info/entry_points.txt
ncs_uml-1.2.2.dist-info/top_level.txt
ncs_uml-1.2.2.dist-info/RECORD
