Metadata-Version: 2.1
Name: ncs-uml
Version: 1.2.2
Summary: The ncs-uml creates plantUML files for the given YANG file and its dependencies
Home-page: https://github.com/kirankotari/ncs-uml.git
Author: Kiran Kumar Kotari
Author-email: kirankotari@live.com
License: UNKNOWN
Keywords: ncs-uml,ncs_uml
Platform: UNKNOWN
Classifier: Development Status :: 5 - Production/Stable
Classifier: Intended Audience :: Developers
Classifier: Topic :: Software Development :: Build Tools
Classifier: License :: OSI Approved :: Apache Software License
Classifier: Operating System :: OS Independent
Classifier: Programming Language :: Python :: 3.5
Classifier: Programming Language :: Python :: 3.6
Classifier: Programming Language :: Python :: 3.7
Classifier: Programming Language :: Python :: 3.8
Classifier: Programming Language :: Python :: 3.9
Classifier: Programming Language :: Python :: 3.10
Classifier: Programming Language :: Python :: 3.11
License-File: LICENSE
Requires-Dist: pyang (>=2.5.0)
